databrewer/__init__.py
databrewer/__main__.py
databrewer/cli.py
databrewer/config.py
databrewer/recipes.py
databrewer/search.py
databrewer/utils.py
databrewer-0.1.1.dist-info/DESCRIPTION.rst
databrewer-0.1.1.dist-info/METADATA
databrewer-0.1.1.dist-info/RECORD
databrewer-0.1.1.dist-info/WHEEL
databrewer-0.1.1.dist-info/entry_points.txt
databrewer-0.1.1.dist-info/metadata.json
databrewer-0.1.1.dist-info/top_level.txt
