Metadata-Version: 2.0
Name: databrewer
Version: 0.1.1
Summary: The missing datasets manager.
Home-page: https://github.com/rolando/databrewer
Author: Rolando (Max) Espinoza
Author-email: rolando@rmax.io
License: MIT
Keywords: databrewer
Platform: UNKNOWN
Classifier: Development Status :: 4 - Beta
Classifier: Intended Audience :: Developers
Classifier: License :: OSI Approved :: MIT License
Classifier: Natural Language :: English
Classifier: Programming Language :: Python :: 2
Classifier: Programming Language :: Python :: 2.7
Classifier: Programming Language :: Python :: 3
Classifier: Programming Language :: Python :: 3.4
Classifier: Programming Language :: Python :: 3.5
Requires-Dist: awesome-slugify (>=1.6)
Requires-Dist: click (<7.0,>=6.0)
Requires-Dist: jsonschema (>=2.5)
Requires-Dist: pyyaml (>=3.0,<4.0)
Requires-Dist: requests (>=2.8)
Requires-Dist: six (>=1.10)
Requires-Dist: toolz
Requires-Dist: tqdm (>=4.0)
Requires-Dist: whoosh (<3.0,>=2.7)
